setup.py
yadi2/__init__.py
yadi2.egg-info/PKG-INFO
yadi2.egg-info/SOURCES.txt
yadi2.egg-info/dependency_links.txt
yadi2.egg-info/not-zip-safe
yadi2.egg-info/requires.txt
yadi2.egg-info/top_level.txt
yadi2/data_structures/__init__.py
yadi2/data_structures/constraint.py
yadi2/data_structures/element.py
yadi2/data_structures/query.py
yadi2/data_structures/relation.py