Metadata-Version: 1.1
Name: yadi2
Version: 0.1.0
Summary: YADI is a Datalog parsing project for the Advanced Databases course                  of the DMKM Erasmus Mundus Masters program.
Home-page: https://github.com/saltzm/yadi
Author: Matthew Saltz
Author-email: saltzm@gmail.com
License: BSD
Keywords: yadi
Platform: UNKNOWN
Classifier: Development Status :: 2 - Pre-Alpha
Classifier: Intended Audience :: Developers
Classifier: License :: OSI Approved :: BSD License
Classifier: Natural Language :: English
Classifier: Programming Language :: Python :: 2
Classifier: Programming Language :: Python :: 2.6
Classifier: Programming Language :: Python :: 2.7
Classifier: Programming Language :: Python :: 3
Classifier: Programming Language :: Python :: 3.3
